CHANGELOG.txt
LICENCE.txt
MANIFEST.in
README.txt
setup.py
somefibonacci/__init__.py
somefibonacci.egg-info/PKG-INFO
somefibonacci.egg-info/SOURCES.txt
somefibonacci.egg-info/dependency_links.txt
somefibonacci.egg-info/top_level.txt